krkr_sprite_synth-0.2.0.dist-info/METADATA
krkr_sprite_synth-0.2.0.dist-info/WHEEL
krkr_sprite_synth-0.2.0.dist-info/entry_points.txt
krkr_sprite_synth-0.2.0.dist-info/licenses/LICENSE
krkr_sprite_synth/__init__.py
krkr_sprite_synth/drawer.py
krkr_sprite_synth/models.py
krkr_sprite_synth/parser.py
krkr_sprite_synth-0.2.0.dist-info/RECORD
