Metadata-Version: 2.1
Name: krkr-sprite-synth
Version: 0.2.0
Summary: A library for synthesizing character sprites for galgame games using the krkr engine
Author-Email: zhaomaoniu <2667292003@qq.com>
License: MIT
Requires-Python: >=3.8
Requires-Dist: Pillow>=10.4.0
